<xml xmlns="http://www.w3.org/1999/xhtml"><variables></variables><block type="program" id="hskGo!n1bYN2t?k(-0]N" x="74" y="-140"><field name="prog_name">sorting</field><next><block type="new_function" id="Xor}gfg0_^z=xiyx)bx$"><field name="func_type">void</field><field name="func_name">sort</field><statement name="content"><block type="lists" id="nCJ09mS-W?Nr9U^]sqXY"><field name="type">int</field><field name="name">v</field><field name="fields">7</field><next><block type="variable_types" id="ESC)m(U.7^x95wI_sQQt"><field name="vars_types">int</field><statement name="variables"><block type="var_new" id="wx,zUi*0N4$OEq/uku{m"><field name="var_name">cont</field><next><block type="var_new" id="hZPe6[9~fejQbUb68oi}"><field name="var_name">temp</field><next><block type="var_new" id="%%u6#/^$i:/9B#xdRv.d"><field name="var_name">i</field><next><block type="var_new" id="U,BGnNX:RdZq|Bh)9uaA"><field name="var_name">j</field></block></next></block></next></block></next></block></statement><next><block type="var_assign" id="THKnibnH,z*29(H%M9Ku"><field name="var_name">cont</field><value name="NAME"><block type="value_input" id="G;h5M_:/R|6MQ7%W0$+J"><field name="value">0</field></block></value><next><block type="var_assign" id="u;[NS~fU!Qdgo,%tuhZ)"><field name="var_name">i</field><value name="NAME"><block type="value_input" id="7[RVW[h~)]Q4%XQDp)yM"><field name="value">0</field></block></value><next><block type="var_assign" id="QwTgq3K,^]ir=we94?-v"><field name="var_name">j</field><value name="NAME"><block type="value_input" id="),;jG)hoo%rL9?YN97j@"><field name="value">0</field></block></value><next><block type="field_assign" id=";A)|7Zv_eV1{YtPcOd?{"><field name="l_name">v</field><field name="NAME">0</field><value name="NAME"><block type="value_input" id="q;q~XFh{I:Y]TO`HCC27"><field name="value">64</field></block></value><next><block type="field_assign" id="n:?4_v!z+*tc{z1i)~Q3"><field name="l_name">v</field><field name="NAME">1</field><value name="NAME"><block type="value_input" id="}#:c_[bs44T{pbO/X;oF"><field name="value">34</field></block></value><next><block type="field_assign" id="c%ailA=XFzJzLRDi%`m9"><field name="l_name">v</field><field name="NAME">2</field><value name="NAME"><block type="value_input" id="HX7r=JwBX2@34B_V958K"><field name="value">25</field></block></value><next><block type="field_assign" id="_+FPZ!u}+5jK!xP+UdE8"><field name="l_name">v</field><field name="NAME">3</field><value name="NAME"><block type="value_input" id="VcZS]mNn0ij;cOn;?vfS"><field name="value">12</field></block></value><next><block type="field_assign" id="J6*3fK=0Q._5.+HX!Y!="><field name="l_name">v</field><field name="NAME">4</field><value name="NAME"><block type="value_input" id="#)gWX5iM##GLMLHXJWU{"><field name="value">22</field></block></value><next><block type="field_assign" id="7!LgDxQKsoDgEjK[-KIr"><field name="l_name">v</field><field name="NAME">5</field><value name="NAME"><block type="value_input" id="I;D/yxLa(~B`gTT299}f"><field name="value">11</field></block></value><next><block type="field_assign" id="Od;5%Mri_+!,jMqDfwsg"><field name="l_name">v</field><field name="NAME">6</field><value name="NAME"><block type="value_input" id="Bu~.d2lc;+cw@krFcw`J"><field name="value">90</field></block></value><next><block type="write" id="X=BB?c8}+=I*v1TpUTip"><value name="NAME"><block type="string_input" id="s4~Dc_~ZCefBqin!bbg]"><field name="value">arreglo antes de bubble sort</field></block></value><next><block type="while" id="#uA$Z*8#P28}4j$%ZaIp"><value name="WHILE"><block type="var_action" id="efPJe3B=^d!hEfxGP#RA"><field name="var_name">cont</field><value name="NAME"><block type="less_than" id="CcRa=XC4bm_6C(vG4=^W"><value name="less_than_text"><block type="value_input" id="X+r~cAu;p8K_(,Z6;{!%"><field name="value">7</field></block></value></block></value></block></value><statement name="DO"><block type="write" id="[28a]+U}Z%^=Yoy0qTa!"><value name="NAME"><block type="access_index" id="fW1h!]~5-$X@:0vY-D0T"><field name="l_name">v</field><field name="NAME">cont</field></block></value><next><block type="var_assign" id="(_DKue6)Qa`H{),}4L40"><field name="var_name">cont</field><value name="NAME"><block type="var_action" id="a4lO.A{?ZaJLtt4)z)zk"><field name="var_name">cont</field><value name="NAME"><block type="plus" id="{P|CAZwKa8,j5[GA;3C]"><value name="plus_text"><block type="value_input" id="7YpV/.oCQj,BPlO0}_/Q"><field name="value">1</field></block></value></block></value></block></value></block></next></block></statement><next><block type="while" id="{;Ol:}#dZt~U0{CGsx],"><value name="WHILE"><block type="var_action" id="u#8,u]Gm@?uX5uaP1iB1"><field name="var_name">i</field><value name="NAME"><block type="less_than" id="Vgc{my%baMSKh#gmdoP]"><value name="less_than_text"><block type="value_input" id="adom#_aLXDWT/(oU9$`4"><field name="value">7</field><value name="value_text"><block type="minus" id="[:kz!1#gdNhK0i~`rTko"><value name="minus_text"><block type="value_input_end" id=":+x`mBP#yD-S%s-gXZD_"><field name="value">1</field></block></value></block></value></block></value></block></value></block></value><statement name="DO"><block type="var_assign" id=",[7pue5BP%6RC#m~j+Q?"><field name="var_name">j</field><value name="NAME"><block type="value_input_end" id="5sk0/Wr:]9X@s#/AEP!V"><field name="value">0</field></block></value><next><block type="while" id="hm~w]eQ:{BkOK3_5=N|2"><value name="WHILE"><block type="var_action" id="4ZjXq]U30i`pxmD8pg!u"><field name="var_name">i</field><value name="NAME"><block type="less_than" id="nKORnlC!E^eqvwk;8{k)"><value name="less_than_text"><block type="value_input" id="3)pbjDL#sDE,``us5w|J"><field name="value">7</field><value name="value_text"><block type="minus" id="D{wtHhZ*hPcYMKAXqSo0"><value name="minus_text"><block type="var_action" id="]+_tS?H?VIZ$NQM/~5UK"><field name="var_name">i</field><value name="NAME"><block type="minus" id="1-n%?*J(,[g,ZM{1(GQ`"><value name="minus_text"><block type="value_input_end" id="Y6C=Ylr+}`K[4;I^q5mF"><field name="value">1</field></block></value></block></value></block></value></block></value></block></value></block></value></block></value><statement name="DO"><block type="if" id="WEv5toqJ]}$)9t}+xQkk"><value name="condition"><block type="access_index" id="/SDCWk2uG=KS+SJXsO(C"><field name="l_name">v</field><field name="NAME">j</field><value name="NAME"><block type="greater_than" id="1rT^|kQ{8h[86V00l,:K"><value name="greater_than"><block type="access_index" id="G/S[x=f0UfR%1Lj(I+|G"><field name="l_name">v</field><field name="NAME">j+1</field></block></value></block></value></block></value><statement name="NAME"><block type="var_assign" id="EZiCNxRK=pADlLZCoae?"><field name="var_name">temp</field><value name="NAME"><block type="access_index" id="zS^duQ(4ao`$KX$m:0m;"><field name="l_name">v</field><field name="NAME">j</field></block></value><next><block type="field_assign" id="F!FMq=3sBzATb9tiDS/Q"><field name="l_name">v</field><field name="NAME">j</field><value name="NAME"><block type="access_index" id="KaCMl/?z^NHafW+Z`^wj"><field name="l_name">v</field><field name="NAME">j+1</field></block></value><next><block type="field_assign" id="h[J?h^Z4I![;hUWT;fgK"><field name="l_name">v</field><field name="NAME">j+1</field><value name="NAME"><block type="var_action" id="K[%zP4U8BWcW^${pHO9Y"><field name="var_name">temp</field></block></value></block></next></block></next></block></statement><next><block type="var_assign" id="EMVE]_1art9jp^+$(:zc"><field name="var_name">j</field><value name="NAME"><block type="var_action" id="oPSb.zcHH#]K%WfiMyiL"><field name="var_name">j</field><value name="NAME"><block type="plus" id="Cbnh#+(}cURKl6fH;=h/"><value name="plus_text"><block type="value_input" id="uf2lRpIjpQnRg!cTXK6g"><field name="value">1</field></block></value></block></value></block></value></block></next></block></statement><next><block type="var_assign" id="ajBE[)+sV7,a7A,qx{1n"><field name="var_name">i</field><value name="NAME"><block type="var_action" id="a)/K4qD)qu6Bb0G^fy/g"><field name="var_name">i</field><value name="NAME"><block type="plus" id="MXHI[f7!7Wr;/J[$iX{I"><value name="plus_text"><block type="value_input" id="T{IEVjfz]B{H{r/TfsCO"><field name="value">1</field></block></value></block></value></block></value></block></next></block></next></block></statement><next><block type="write" id="eG2Bx6LN4]N2NooQyu`K"><value name="NAME"><block type="string_input" id="NnX}P-={SesoR3//UxXJ"><field name="value">arreglo antes de bubble sort</field></block></value><next><block type="var_assign" id="(*8*KM4k0KpCFT%[Dw65"><field name="var_name">cont</field><value name="NAME"><block type="value_input_end" id="06W2RIHO]MZA2DJ!@nPb"><field name="value">0</field></block></value><next><block type="while" id="^N0b=P~|2ON;Ss~kP4z-"><value name="WHILE"><block type="var_action" id="E|#fgFcTeQ]5TUS*Rs(Q"><field name="var_name">cont</field><value name="NAME"><block type="less_than" id="eyIx9Jg4Ru;;zKQ3JIKm"><value name="less_than_text"><block type="value_input" id="Px].UK@dkZ6[E~E;SF0y"><field name="value">7</field></block></value></block></value></block></value><statement name="DO"><block type="write" id="h{n(S?U:9#j@ANUYxUkW"><value name="NAME"><block type="access_index" id="K]g,9]`9hdUg:7+:g5R%"><field name="l_name">v</field><field name="NAME">cont</field></block></value><next><block type="var_assign" id="27DVo)S.1!}2]u%._(*6"><field name="var_name">cont</field><value name="NAME"><block type="var_action" id="3~VM@nmAc3fUJ6MHt7*b"><field name="var_name">cont</field><value name="NAME"><block type="plus" id="JAdt/Y$5C6Y$+?lBOD4g"><value name="plus_text"><block type="value_input" id="N7i~N3dVSSyugc_v8D]p"><field name="value">1</field></block></value></block></value></block></value></block></next></block></statement></block></next></block></next></block></next></block></next></block></next></block></next></block></next></block></next></block></next></block></next></block></next></block></next></block></next></block></next></block></next></block></next></block></next></block></statement></block></next></block></xml>